umnet_gspread/__init__.py
umnet_gspread-0.2.0.dist-info/LICENSE
umnet_gspread-0.2.0.dist-info/METADATA
umnet_gspread-0.2.0.dist-info/WHEEL
umnet_gspread-0.2.0.dist-info/RECORD
