Metadata-Version: 2.3
Name: umnet-gspread
Version: 0.2.0
Summary: UMNet google spreadsheet helpers
License: MIT
Author: Amy Liebowitz
Author-email: amylieb@umich.edu
Requires-Python: >=3.9
Classifier: License :: OSI Approved :: MIT License
Classifier: Programming Language :: Python :: 3
Classifier: Programming Language :: Python :: 3.9
Classifier: Programming Language :: Python :: 3.10
Classifier: Programming Language :: Python :: 3.11
Classifier: Programming Language :: Python :: 3.12
Classifier: Programming Language :: Python :: 3.13
Requires-Dist: gspread (>=6.2.1,<7.0.0)
Requires-Dist: oauth2client (>=4.1.3,<5.0.0)
Requires-Dist: pydantic (>=2.11.9,<3.0.0)
Requires-Dist: umnet-cyberark (>=0.1.0,<0.2.0)
